{
  "ingredient": "Sodium Citrate",
  "search_results": [
    {
      "identifier": "11339",
      "inci_name": "SODIUM CITRATE"
    },
    {
      "identifier": "1917",
      "inci_name": "SODIUM DILAURETH-7 CITRATE"
    }
  ],
  "detailed_info": [
    {
      "id": 11339,
      "inci_name": "SODIUM CITRATE",
      "name": "Sodium citrate",
      "description": "Sodium citrate is a sodium salt of citric acid. It is generally used in cosmetics as a PH regulator. It is authorized in Bio.",
      "regulation": "",
      "reference": "",
      "cheminical_iupac_name": "",
      "cas": "68-04-2 / 6132-04-3",
      "einecs_elincs": "200-675-3",
      "cosmetic_restriction": "",
      "percentage": 4.15,
      "category_percentage": [
        {
          "category_name": "Classic shampoo",
          "percentage": "9.98",
          "count": 2328
        },
        {
          "category_name": "Anti-dandruff shampoo",
          "percentage": "38.72",
          "count": 1075
        },
        {
          "category_name": "Foundation",
          "percentage": "9",
          "count": 937
        },
        {
          "category_name": "Face cream",
          "percentage": "7.68",
          "count": 861
        },
        {
          "category_name": "Body milk and cream",
          "percentage": "4.16",
          "count": 642
        }
      ],
      "score": 0,
      "origin": [
        {
          "name": "Vegetal"
        },
        {
          "name": "Synthetic"
        }
      ],
      "families": [],
      "functions": [
        {
          "name": "pH regulator",
          "description": "Stabilises the pH of cosmetics"
        },
        {
          "name": "Chelating",
          "description": "Reacts and forms complexes with metal ions that could affect the stability and / or appearance of cosmetic products"
        },
        {
          "name": "Masking",
          "description": "Reduces or inhibits the odor or basic taste of the product"
        }
      ],
      "dangers": [
        {
          "value": 0,
          "label": "\"No penalty\" in all categories."
        }
      ]
    },
    {
      "id": 1917,
      "inci_name": "SODIUM DILAURETH-7 CITRATE",
      "name": null,
      "description": "",
      "regulation": "",
      "reference": "",
      "cheminical_iupac_name": "",
      "cas": "",
      "einecs_elincs": "",
      "cosmetic_restriction": "",
      "percentage": 0.01,
      "category_percentage": [],
      "score": 5,
      "origin": [],
      "families": [
        {
          "id": 12,
          "name": "Ethoxylated compound",
          "score": 5
        }
      ],
      "functions": [
        {
          "name": "Cleansing",
          "description": "Helps to keep a clean surface"
        },
        {
          "name": "Emulsifying",
          "description": "Promotes the formation of intimate mixtures between immiscible liquids by modifying the interfacial tension (water and oil)"
        },
        {
          "name": "Surfactant",
          "description": "Reduces the surface tension of cosmetics and contributes to the even distribution of the product when it is used"
        }
      ],
      "dangers": [
        {
          "value": 5,
          "label": "\"Medium penalty\" in all categories."
        }
      ]
    }
  ]
}